extranatapi/__init__.py
extranatapi/base.py
extranatapi/cli.py
extranatapi/competition.py
extranatapi/conftest.py
extranatapi/cotation.py
extranatapi/extranatcli.py
extranatapi/filetools.py
extranatapi/location.py
extranatapi/nageur.py
extranatapi/rechercheequipe.py
extranatapi/saison.py
extranatapi/tools.py
extranatapi/wrapper.py
extranatapi-0.0.0.7.dist-info/LICENSE
extranatapi-0.0.0.7.dist-info/METADATA
extranatapi-0.0.0.7.dist-info/WHEEL
extranatapi-0.0.0.7.dist-info/entry_points.txt
extranatapi-0.0.0.7.dist-info/top_level.txt
extranatapi-0.0.0.7.dist-info/RECORD
