Metadata-Version: 2.1
Name: extranatapi
Version: 0.0.0.7
Summary: Extranat API
Home-page: https://gitlab.com/doudoux-g/extranatapi
Author: Doudoux
Project-URL: Bug Tracker, https://gitlab.com/doudoux-g/extranatapi/-/issues
Classifier: Programming Language :: Python :: 3
Classifier: License :: OSI Approved :: MIT License
Classifier: Operating System :: OS Independent
Requires-Python: >=3.6
License-File: LICENSE
Requires-Dist: beautifulsoup4
Requires-Dist: openpyxl
